walrus/__init__.py
walrus/_version.py
walrus/greet.py
walrus/math.py
walrus/movies.py
walrus/data/__init__.py
walrus/data/greeting.txt
walrus/data/oscars_df.csv
vineetb_walrus-0.3.0.dist-info/METADATA
vineetb_walrus-0.3.0.dist-info/WHEEL
vineetb_walrus-0.3.0.dist-info/top_level.txt
vineetb_walrus-0.3.0.dist-info/RECORD
